eindata/__about__.py
eindata/__init__.py
eindata-0.0.2.dist-info/METADATA
eindata-0.0.2.dist-info/WHEEL
eindata-0.0.2.dist-info/licenses/LICENSE.txt
eindata-0.0.2.dist-info/RECORD
