Metadata-Version: 2.3
Name: eindata
Version: 0.0.2
Summary: Data wrangling and exploratory data analysis awith elegant einops-inspired syntax.
Project-URL: Documentation, https://github.com/mbodiai/eindata#readme
Project-URL: Issues, https://github.com/mbodiai/eindata/issues
Project-URL: Source, https://github.com/mbodiai/eindata
Author-email: mbodi team <info@mbodi.ai>
License-Expression: Apache-2.0
License-File: LICENSE.txt
Classifier: Programming Language :: Python :: 3.10
Classifier: Programming Language :: Python :: 3.11
Classifier: Programming Language :: Python :: 3.12
Classifier: Programming Language :: Python :: Implementation :: CPython
Classifier: Programming Language :: Python :: Implementation :: PyPy
Requires-Python: >=3.10
